dataxtractor-1.4.10.dist-info/licenses/LICENSE
image_dataextraction/__init__.py
image_dataextraction/data_imageextraction.py
pdf2image_dataextraction/__init__.py
pdf2image_dataextraction/data_extract.py
pdf2image_dataextraction/data_extraction2parts.py
pdf_dataextraction/__init__.py
pdf_dataextraction/data_extraction_pdf.py
dataxtractor-1.4.10.dist-info/METADATA
dataxtractor-1.4.10.dist-info/WHEEL
dataxtractor-1.4.10.dist-info/top_level.txt
dataxtractor-1.4.10.dist-info/RECORD
