Metadata-Version: 2.4
Name: DataXtractor
Version: 1.4.10
Summary: DataXtractor is a versatile Python library designed to simplify the extraction of valuable data from a variety of sources, including images and PDF documents. Whether you need to extract text, tables, or structured content, DataXtractor provides powerful and intuitive tools to streamline the process.
Home-page: https://github.com/Rahulkatoch99/dataxtractor
Author: Rahul Katoch
Author-email: Rahul Katoch <rahulkatoch99@gmail.com>
Maintainer: Rahul Katoch, Harish Kumar
Maintainer-email: Rahul Katoch <rahulkatoch99@gmail.com>, Harish Kumar <mr.harishkumar@protonmail.com>
License: MIT
Project-URL: Homepage, https://github.com/Rahulkatoch99/dataxtractor
Keywords: data,extraction,pdf,image,xls extraction,pdf extrcation,ocr
Classifier: Development Status :: 5 - Production/Stable
Classifier: Intended Audience :: Developers
Classifier: License :: OSI Approved :: MIT License
Classifier: Programming Language :: Python :: 3
Classifier: Programming Language :: Python :: 3.6
Classifier: Programming Language :: Python :: 3.7
Classifier: Programming Language :: Python :: 3.8
Classifier: Programming Language :: Python :: 3.9
Classifier: Programming Language :: Python :: 3.10
Requires-Python: >=3.6
License-File: LICENSE
Requires-Dist: wheel
Requires-Dist: opencv-python
Requires-Dist: pytesseract
Requires-Dist: pdf2image
Requires-Dist: pdftotext
Requires-Dist: pdfplumber
Requires-Dist: pdfminer.six
Requires-Dist: pandas
Requires-Dist: altair==5.4.1
Requires-Dist: attrs==24.2.0
Requires-Dist: beautifulsoup4==4.12.3
Requires-Dist: typing_extensions==4.12.2
Requires-Dist: tzdata==2024.2
Requires-Dist: urllib3==2.2.3
Requires-Dist: watchdog==5.0.3
Requires-Dist: xlrd==2.0.1
Requires-Dist: XlsxWriter==3.2.0
Requires-Dist: Spire.Xls==14.7.3
Dynamic: license-file
